[
  {
    "policyId": "policy-cancellation",
    "name": "Политика отмены и возврата",
    "type": "cancellation",
    "content": "1. Разовые посещения: возврат не предусмотрен после начала рабочего дня.\n2. Абонементы: отмена возможна до 25 числа предыдущего месяца. При отмене после 25 числа — абонемент действует до конца оплаченного периода без возврата.\n3. Переговорные: бесплатная отмена за 2 часа до начала. При отмене менее чем за 2 часа — списывается 50% стоимости. Неявка — полная оплата.\n4. Мероприятия: бесплатная отмена за 5 дней. За 3-5 дней — возврат 50%. Менее 3 дней — без возврата.\n5. Виртуальный офис: расторжение договора за 30 дней с уведомлением в письменной форме.\n6. Все возвраты обрабатываются в течение 5 рабочих дней.\n7. Форс-мажор: при обстоятельствах непреодолимой силы возможен полный возврат по согласованию с управляющей.",
    "summary": "Отмена абонементов до 25 числа предыдущего месяца. Переговорные — бесплатная отмена за 2 часа. Мероприятия — за 5 дней. Возвраты в течение 5 рабочих дней.",
    "keyPoints": [
      "Абонемент: отмена до 25 числа предыдущего месяца",
      "Переговорная: бесплатная отмена за 2 часа",
      "Мероприятие: бесплатная отмена за 5 дней",
      "Возвраты обрабатываются за 5 рабочих дней",
      "Неявка на переговорную — полная оплата",
      "Виртуальный офис — уведомление за 30 дней"
    ],
    "lastUpdated": 1704067200000,
    "metadata": {
      "version": "2.1",
      "approvedBy": "Анна Петрова"
    }
  }
]
